{
    "language": "English",
    "languageCode": "en",
    "entries": [
        { "key": "common.hello", "value": "Hello" },
        { "key": "common.welcome", "value": "Welcome" },
        { "key": "common.thank_you", "value": "Thank you" },
        { "key": "common.yes", "value": "Yes" },
        { "key": "common.no", "value": "No" },
        { "key": "common.ok", "value": "OK" },
        { "key": "common.cancel", "value": "Cancel" },
        { "key": "common.confirm", "value": "Confirm" },
        { "key": "common.save", "value": "Save" },
        { "key": "common.load", "value": "Load" },
        { "key": "common.delete", "value": "Delete" },
        { "key": "common.edit", "value": "Edit" },
        { "key": "common.back", "value": "Back" },
        { "key": "common.next", "value": "Next" },
        { "key": "common.previous", "value": "Previous" },
        { "key": "common.close", "value": "Close" },
        { "key": "common.settings", "value": "Settings" },
        { "key": "common.help", "value": "Help" },
        { "key": "common.loading", "value": "Loading..." },
        { "key": "common.error", "value": "Error" },
        { "key": "common.success", "value": "Success" },
        { "key": "common.warning", "value": "Warning" },
        { "key": "common.retry", "value": "Retry" },

        { "key": "menu.play", "value": "Play" },
        { "key": "menu.continue", "value": "Continue" },
        { "key": "menu.new_game", "value": "New Game" },
        { "key": "menu.options", "value": "Options" },
        { "key": "menu.credits", "value": "Credits" },
        { "key": "menu.quit", "value": "Quit" },
        { "key": "menu.pause", "value": "Pause" },
        { "key": "menu.resume", "value": "Resume" },
        { "key": "menu.main_menu", "value": "Main Menu" },

        { "key": "settings.audio", "value": "Audio" },
        { "key": "settings.graphics", "value": "Graphics" },
        { "key": "settings.controls", "value": "Controls" },
        { "key": "settings.language", "value": "Language" },
        { "key": "settings.account", "value": "Account" },
        { "key": "settings.notifications", "value": "Notifications" },
        { "key": "settings.privacy", "value": "Privacy" },
        { "key": "settings.master_volume", "value": "Master Volume" },
        { "key": "settings.music_volume", "value": "Music Volume" },
        { "key": "settings.sfx_volume", "value": "Sound Effects" },
        { "key": "settings.vibration", "value": "Vibration" },
        { "key": "settings.reset_defaults", "value": "Reset to Defaults" },

        { "key": "game.level", "value": "Level" },
        { "key": "game.score", "value": "Score" },
        { "key": "game.time", "value": "Time" },
        { "key": "game.health", "value": "Health" },
        { "key": "game.energy", "value": "Energy" },
        { "key": "game.coins", "value": "Coins" },
        { "key": "game.gems", "value": "Gems" },
        { "key": "game.experience", "value": "Experience" },
        { "key": "game.rank", "value": "Rank" },

        { "key": "building.citadel", "value": "Citadel" },
        { "key": "building.tower", "value": "Tower" },
        { "key": "building.wall", "value": "Wall" },
        { "key": "building.gate", "value": "Gate" },
        { "key": "building.barracks", "value": "Barracks" },
        { "key": "building.resource_node", "value": "Resource Node" },
        { "key": "building.upgrade", "value": "Upgrade" },
        { "key": "building.build", "value": "Build" },
        { "key": "building.demolish", "value": "Demolish" },
        { "key": "building.repair", "value": "Repair" },
        { "key": "building.level_format", "value": "Level {0}" },
        { "key": "building.cost_format", "value": "Cost: {0}" },
        { "key": "building.time_format", "value": "Build Time: {0}" },

        { "key": "combat.attack", "value": "Attack" },
        { "key": "combat.defend", "value": "Defend" },
        { "key": "combat.retreat", "value": "Retreat" },
        { "key": "combat.victory", "value": "Victory!" },
        { "key": "combat.defeat", "value": "Defeat" },
        { "key": "combat.draw", "value": "Draw" },
        { "key": "combat.damage", "value": "Damage" },
        { "key": "combat.critical", "value": "Critical Hit!" },
        { "key": "combat.miss", "value": "Miss" },

        { "key": "territory.claim", "value": "Claim Territory" },
        { "key": "territory.contested", "value": "Contested" },
        { "key": "territory.owned", "value": "Owned" },
        { "key": "territory.neutral", "value": "Neutral" },
        { "key": "territory.capture_progress", "value": "Capture Progress: {0}%" },

        { "key": "alliance.create", "value": "Create Alliance" },
        { "key": "alliance.join", "value": "Join Alliance" },
        { "key": "alliance.leave", "value": "Leave Alliance" },
        { "key": "alliance.invite", "value": "Invite" },
        { "key": "alliance.kick", "value": "Kick" },
        { "key": "alliance.promote", "value": "Promote" },
        { "key": "alliance.demote", "value": "Demote" },
        { "key": "alliance.members", "value": "Members" },
        { "key": "alliance.chat", "value": "Alliance Chat" },
        { "key": "alliance.war", "value": "Alliance War" },

        { "key": "resource.gold", "value": "Gold" },
        { "key": "resource.stone", "value": "Stone" },
        { "key": "resource.wood", "value": "Wood" },
        { "key": "resource.iron", "value": "Iron" },
        { "key": "resource.food", "value": "Food" },
        { "key": "resource.collect", "value": "Collect" },
        { "key": "resource.production", "value": "Production: {0}/hr" },

        { "key": "player.profile", "value": "Profile" },
        { "key": "player.stats", "value": "Stats" },
        { "key": "player.inventory", "value": "Inventory" },
        { "key": "player.achievements", "value": "Achievements" },
        { "key": "player.leaderboard", "value": "Leaderboard" },
        { "key": "player.friends", "value": "Friends" },

        { "key": "ar.scan_environment", "value": "Scan your environment" },
        { "key": "ar.place_object", "value": "Tap to place" },
        { "key": "ar.move_closer", "value": "Move closer to the surface" },
        { "key": "ar.tracking_lost", "value": "Tracking lost, please scan again" },
        { "key": "ar.anchor_saved", "value": "Location saved" },
        { "key": "ar.anchor_loading", "value": "Loading saved location..." },

        { "key": "notification.daily_reward", "value": "Your daily reward is ready!" },
        { "key": "notification.building_complete", "value": "{0} construction complete!" },
        { "key": "notification.under_attack", "value": "Your territory is under attack!" },
        { "key": "notification.alliance_request", "value": "{0} wants to join your alliance" },

        { "key": "tutorial.welcome", "value": "Welcome to Apex Citadels!" },
        { "key": "tutorial.tap_continue", "value": "Tap to continue" },
        { "key": "tutorial.first_building", "value": "Let's build your first structure" },
        { "key": "tutorial.claim_territory", "value": "Claim this territory as your own" },
        { "key": "tutorial.complete", "value": "Tutorial Complete!" },

        { "key": "error.connection_failed", "value": "Connection failed. Please check your internet." },
        { "key": "error.server_error", "value": "Server error. Please try again later." },
        { "key": "error.session_expired", "value": "Session expired. Please log in again." },
        { "key": "error.not_enough_resources", "value": "Not enough resources" },
        { "key": "error.invalid_action", "value": "Invalid action" },

        { "key": "time.seconds", "value": "{0}s" },
        { "key": "time.minutes", "value": "{0}m" },
        { "key": "time.hours", "value": "{0}h" },
        { "key": "time.days", "value": "{0}d" },
        { "key": "time.just_now", "value": "Just now" },
        { "key": "time.ago", "value": "{0} ago" }
    ]
}
